Oasys/D3PLOT/__init__.py
Oasys/D3PLOT/beam.py
Oasys/D3PLOT/colour.py
Oasys/D3PLOT/component.py
Oasys/D3PLOT/constant.py
Oasys/D3PLOT/contact.py
Oasys/D3PLOT/core.py
Oasys/D3PLOT/funcs.py
Oasys/D3PLOT/graphicswindow.py
Oasys/D3PLOT/group.py
Oasys/D3PLOT/image.py
Oasys/D3PLOT/include.py
Oasys/D3PLOT/itemobject.py
Oasys/D3PLOT/material.py
Oasys/D3PLOT/measure.py
Oasys/D3PLOT/model.py
Oasys/D3PLOT/node.py
Oasys/D3PLOT/options.py
Oasys/D3PLOT/page.py
Oasys/D3PLOT/part.py
Oasys/D3PLOT/segment.py
Oasys/D3PLOT/setbeam.py
Oasys/D3PLOT/setnode.py
Oasys/D3PLOT/setpart.py
Oasys/D3PLOT/setshell.py
Oasys/D3PLOT/setsolid.py
Oasys/D3PLOT/settshell.py
Oasys/D3PLOT/shell.py
Oasys/D3PLOT/solid.py
Oasys/D3PLOT/tshell.py
Oasys/D3PLOT/type.py
Oasys/D3PLOT/utils.py
Oasys/D3PLOT/view.py
Oasys/D3PLOT/window.py
Oasys/D3PLOT/workflow.py
oasys_d3plot-22.1.0.dist-info/licenses/LICENSE
oasys_d3plot-22.1.0.dist-info/METADATA
oasys_d3plot-22.1.0.dist-info/WHEEL
oasys_d3plot-22.1.0.dist-info/top_level.txt
oasys_d3plot-22.1.0.dist-info/RECORD
